arris_tg2492lg/__init__.py
arris_tg2492lg/connect_box.py
arris_tg2492lg/const.py
arris_tg2492lg/device.py
arris_tg2492lg/exception.py
arris_tg2492lg/mib_mapper.py
arris_tg2492lg-2.1.0.dist-info/LICENSE
arris_tg2492lg-2.1.0.dist-info/METADATA
arris_tg2492lg-2.1.0.dist-info/WHEEL
arris_tg2492lg-2.1.0.dist-info/top_level.txt
arris_tg2492lg-2.1.0.dist-info/RECORD
