Metadata-Version: 2.1
Name: arris-tg2492lg
Version: 2.1.0
Summary: Python client for the Arris TG2492LG
Home-page: https://github.com/vanbalken/arris-tg2492lg
Author: vanbalken
License: UNKNOWN
Platform: UNKNOWN
Classifier: Programming Language :: Python :: 3
Classifier: License :: OSI Approved :: MIT License
Classifier: Operating System :: OS Independent
Requires-Python: >=3.7
License-File: LICENSE
